{"cameraMode":{"drawMode":0,"name":"Shaded","section":"Shading Mode"},"sceneLighting":true,"audioPlay":false,"sceneViewState":{"m_AlwaysRefresh":false,"showFog":true,"showSkybox":true,"showFlares":true,"showImageEffects":true,"showParticleSystems":true,"showVisualEffectGraphs":true,"m_FxEnabled":true},"in2DMode":false,"pivot":{"x":-120.0433120727539,"y":-19.83597183227539,"z":-82.31226348876953},"rotation":{"x":-0.068931445479393,"y":0.8857038021087647,"z":-0.13958191871643067,"w":-0.4373871982097626},"size":143.85317993164063,"orthographic":false}